AUTHORS
CHANGELOG.md
LICENSE
README.md
django_fast_migrations/__init__.py
django_fast_migrations/management/__init__.py
django_fast_migrations/management/commands/__init__.py
django_fast_migrations/management/commands/migrate_by_app.py
django_fast_migrations-0.1.0.dist-info/LICENSE
django_fast_migrations-0.1.0.dist-info/WHEEL
django_fast_migrations-0.1.0.dist-info/METADATA
django_fast_migrations-0.1.0.dist-info/RECORD
