Metadata-Version: 2.1
Name: django-fast-migrations
Version: 0.1.0
Summary: 
Home-page: UNKNOWN
License: MIT
Author: Andreu Vallbona
Author-email: avallbona@apsl.net
Classifier: License :: OSI Approved :: MIT License
Classifier: Programming Language :: Python :: 2
Classifier: Programming Language :: Python :: 2.7
Classifier: Programming Language :: Python :: 3
Classifier: Programming Language :: Python :: 3.4
Classifier: Programming Language :: Python :: 3.5
Classifier: Programming Language :: Python :: 3.6
Classifier: Programming Language :: Python :: 3.7
Requires-Dist: django (>=1.8)
